[{"id":5738,"date":"2022-10-18T16:35:50","date_gmt":"2022-10-18T14:35:50","guid":{"rendered":"https:\/\/biblioteca-wp.sgi-italia.org\/rsnd\/risposta-a-nishiyama-2\/"},"modified":"2023-03-27T19:33:31","modified_gmt":"2023-03-27T17:33:31","slug":"risposta-a-nishiyama-2","status":"publish","type":"rsnd","link":"https:\/\/biblioteca-wp.sgi-italia.org\/rsnd\/risposta-a-nishiyama-2\/","title":{"rendered":"Risposta a Nishiyama"},"content":{"rendered":"\n<p>Ormai da diverso tempo, pensando alla tua prossima esistenza, tu hai dimostrato molta sincerit\u00e0 nella ricerca della via e per questo ti ho detto solo i nomi degli insegnamenti. Riguardo a essi dovresti chiedere ulteriori dettagli ai tuoi compagni di fede. Poich\u00e9 si tratta di una cosa facile da capire, non occorre una gran saggezza, non occorre una gran saggezza.<\/p>\n\n\n\n<p>Con profondo rispetto,<\/p>\n\n\n\n<p>Nichiren<\/p>\n\n\n\n<p>Il ventitreesimo giorno del primo mese<\/p>\n\n\n\n<p>Risposta a Nishiyama<\/p>\n","protected":false},"featured_media":0,"parent":0,"menu_order":0,"template":"","meta":{"inline_featured_image":false,"ep_exclude_from_search":false},"cat_rsnd":[17],"acf":{"acf_note":"","acf_numero":"406.","acf_cenni_storici":"<p>L\u2019anno in cui fu scritta questa lettera non ci \u00e8 noto e tutto ci\u00f2 che resta \u00e8 un frammento dell\u2019ultima pagina. La lettera \u00e8 indirizzata al prete laico di Nishiyama, un seguace di Nichiren Daishonin che risiedeva a Nishiyama nel distretto di Fuji, provincia di Suruga. Il Daishonin loda il suo desiderio di raggiungere la via, cio\u00e8 di ottenere l\u2019illuminazione, pensando alla sua esistenza futura, e lo incoraggia a ricercare ulteriori spiegazioni sulla terminologia dai suoi compagni di fede.<\/p>","acf_data":"Data sconosciuta","acf_destinatario":["Nishiyama, prete laico"],"acf_luogo":"Luogo sconosciuto"},"_links":{"self":[{"href":"https:\/\/biblioteca-wp.sgi-italia.org\/wp-json\/wp\/v2\/rsnd\/5738"}],"collection":[{"href":"https:\/\/biblioteca-wp.sgi-italia.org\/wp-json\/wp\/v2\/rsnd"}],"about":[{"href":"https:\/\/biblioteca-wp.sgi-italia.org\/wp-json\/wp\/v2\/types\/rsnd"}],"wp:attachment":[{"href":"https:\/\/biblioteca-wp.sgi-italia.org\/wp-json\/wp\/v2\/media?parent=5738"}],"wp:term":[{"taxonomy":"cat_rsnd","embeddable":true,"href":"https:\/\/biblioteca-wp.sgi-italia.org\/wp-json\/wp\/v2\/cat_rsnd?post=5738"}],"curies":[{"name":"wp","href":"https:\/\/api.w.org\/{rel}","templated":true}]}}]